Metadata-Version: 1.1
Name: cm
Version: 0.1a0
Summary: Commandline Magic
Home-page: UNKNOWN
Author: Dmitry Orlov <me@mosquito.su>
Author-email: me@mosquito.su
License: MIT
Platform: all
Classifier: Environment :: Console
Classifier: Programming Language :: Python
